maicos/__init__.py
maicos/__main__.py
maicos/_version.py
maicos/core/__init__.py
maicos/core/base.py
maicos/core/cylinder.py
maicos/core/planar.py
maicos/core/sphere.py
maicos/lib/__init__.py
maicos/lib/_cmath.c
maicos/lib/_cmath.cp311-win_amd64.pyd
maicos/lib/_cmath.pyx
maicos/lib/math.py
maicos/lib/tables.py
maicos/lib/util.py
maicos/lib/weights.py
maicos/modules/__init__.py
maicos/modules/densitycylinder.py
maicos/modules/densityplanar.py
maicos/modules/densitysphere.py
maicos/modules/dielectriccylinder.py
maicos/modules/dielectricplanar.py
maicos/modules/dielectricspectrum.py
maicos/modules/dielectricsphere.py
maicos/modules/dipoleangle.py
maicos/modules/dipordercylinder.py
maicos/modules/diporderplanar.py
maicos/modules/dipordersphere.py
maicos/modules/diporderstructurefactor.py
maicos/modules/kineticenergy.py
maicos/modules/pdfcylinder.py
maicos/modules/pdfplanar.py
maicos/modules/rdfdiporder.py
maicos/modules/saxs.py
maicos/modules/temperatureplanar.py
maicos/modules/velocitycylinder.py
maicos/modules/velocityplanar.py
maicos/share/scatteringfactors.dat
maicos-0.11.2.dist-info/licenses/AUTHORS.rst
maicos-0.11.2.dist-info/licenses/LICENSE
maicos-0.11.2.dist-info/METADATA
maicos-0.11.2.dist-info/WHEEL
maicos-0.11.2.dist-info/entry_points.txt
maicos-0.11.2.dist-info/top_level.txt
maicos-0.11.2.dist-info/RECORD
