Metadata-Version: 2.4
Name: maicos
Version: 0.11.2
Summary: Analyse molecular dynamics simulations of interfacial and confined systems.
Author: MAICoS Developer Team
Maintainer: Philip Loche, Henrik Stooß, Alexander Schlaich
License-Expression: GPL-3.0-or-later
Project-URL: homepage, https://www.maicos-analysis.org
Project-URL: documentation, https://maicos-analysis.org
Project-URL: repository, https://github.com/maicos-devel/maicos
Project-URL: changelog, https://maicos-analysis.org/stable/get-started/changelog.html
Project-URL: issues, https://github.com/maicos-devel/maicos/issues
Project-URL: discord, https://discord.gg/mnrEQWVAed
Project-URL: twitter, https://twitter.com/maicos_analysis
Keywords: Science,Molecular Dynamics,Confined Systems,MDAnalysis
Classifier: Development Status :: 4 - Beta
Classifier: Environment :: Console
Classifier: Intended Audience :: Science/Research
Classifier: Operating System :: POSIX
Classifier: Operating System :: MacOS :: MacOS X
Classifier: Operating System :: Microsoft :: Windows
Classifier: Programming Language :: Python
Classifier: Programming Language :: Python :: 3
Classifier: Programming Language :: Python :: 3.10
Classifier: Programming Language :: Python :: 3.11
Classifier: Programming Language :: Python :: 3.12
Classifier: Programming Language :: Python :: 3.13
Classifier: Topic :: Scientific/Engineering
Classifier: Topic :: Scientific/Engineering :: Bio-Informatics
Classifier: Topic :: Scientific/Engineering :: Chemistry
Classifier: Topic :: Scientific/Engineering :: Physics
Classifier: Topic :: Software Development :: Libraries :: Python Modules
Classifier: Topic :: System :: Shells
Requires-Python: >=3.10
License-File: LICENSE
License-File: AUTHORS.rst
Requires-Dist: mdacli>=0.1.28
Requires-Dist: MDAnalysis>=2.8.0
Requires-Dist: typing_extensions
Provides-Extra: examples
Requires-Dist: matplotlib; extra == "examples"
Dynamic: license-file
